{"annotations": [{"instanceUID": "2.25.147954431933806485305686905800465263033", "blocks": [{"code": 11, "description": "", "states": ["H"], "points": [{"x": 1335, "y": 607}, {"x": 1335, "y": 867}, {"x": 1439, "y": 867}, {"x": 1439, "y": 607}], "mask": []}, {"code": 21, "description": "", "states": ["H"], "points": [{"x": 1433, "y": 592}, {"x": 1433, "y": 872}, {"x": 1518, "y": 872}, {"x": 1518, "y": 592}], "mask": []}, {"code": 22, "description": "", "states": ["H"], "points": [{"x": 1506, "y": 582}, {"x": 1506, "y": 868}, {"x": 1595, "y": 868}, {"x": 1595, "y": 582}], "mask": []}, {"code": 23, "description": "", "states": ["H"], "points": [{"x": 1594, "y": 588}, {"x": 1594, "y": 861}, {"x": 1688, "y": 861}, {"x": 1688, "y": 588}], "mask": []}, {"code": 24, "description": "", "states": ["H"], "points": [{"x": 1673, "y": 597}, {"x": 1673, "y": 857}, {"x": 1771, "y": 857}, {"x": 1771, "y": 597}], "mask": []}, {"code": 25, "description": "", "states": ["H"], "points": [{"x": 1743, "y": 613}, {"x": 1743, "y": 855}, {"x": 1846, "y": 855}, {"x": 1846, "y": 613}], "mask": []}, {"code": 26, "description": "", "states": ["H"], "points": [{"x": 1835, "y": 582}, {"x": 1835, "y": 843}, {"x": 1967, "y": 843}, {"x": 1967, "y": 582}], "mask": []}, {"code": 27, "description": "", "states": ["H"], "points": [{"x": 1962, "y": 584}, {"x": 1962, "y": 842}, {"x": 2086, "y": 842}, {"x": 2086, "y": 584}], "mask": []}, {"code": 12, "description": "", "states": ["H"], "points": [{"x": 1270, "y": 577}, {"x": 1270, "y": 848}, {"x": 1352, "y": 848}, {"x": 1352, "y": 577}], "mask": []}, {"code": 13, "description": "", "states": ["H"], "points": [{"x": 1180, "y": 590}, {"x": 1180, "y": 851}, {"x": 1276, "y": 851}, {"x": 1276, "y": 590}], "mask": []}, {"code": 14, "description": "", "states": ["H"], "points": [{"x": 1099, "y": 621}, {"x": 1099, "y": 866}, {"x": 1195, "y": 866}, {"x": 1195, "y": 621}], "mask": []}, {"code": 15, "description": "", "states": ["H"], "points": [{"x": 1024, "y": 595}, {"x": 1024, "y": 839}, {"x": 1110, "y": 839}, {"x": 1110, "y": 595}], "mask": []}, {"code": 16, "description": "", "states": ["H"], "points": [{"x": 906, "y": 577}, {"x": 906, "y": 836}, {"x": 1035, "y": 836}, {"x": 1035, "y": 577}], "mask": []}, {"code": 17, "description": "", "states": ["H"], "points": [{"x": 849, "y": 533}, {"x": 767, "y": 809}, {"x": 894, "y": 851}, {"x": 976, "y": 574}], "mask": []}, {"code": 18, "description": "", "states": ["M3i", "H"], "points": [{"x": 823, "y": 513}, {"x": 729, "y": 674}, {"x": 818, "y": 725}, {"x": 912, "y": 564}], "mask": []}, {"code": 37, "description": "", "states": ["H"], "points": [{"x": 1898, "y": 893}, {"x": 2010, "y": 1153}, {"x": 2143, "y": 1095}, {"x": 2031, "y": 836}], "mask": []}, {"code": 36, "description": "", "states": ["H"], "points": [{"x": 1753, "y": 910}, {"x": 1832, "y": 1176}, {"x": 1997, "y": 1128}, {"x": 1917, "y": 861}], "mask": []}, {"code": 35, "description": "", "states": ["H"], "points": [{"x": 1696, "y": 884}, {"x": 1696, "y": 1159}, {"x": 1793, "y": 1159}, {"x": 1793, "y": 884}], "mask": []}, {"code": 34, "description": "", "states": ["H"], "points": [{"x": 1610, "y": 886}, {"x": 1610, "y": 1155}, {"x": 1693, "y": 1155}, {"x": 1693, "y": 886}], "mask": []}, {"code": 33, "description": "", "states": ["H"], "points": [{"x": 1528, "y": 885}, {"x": 1528, "y": 1148}, {"x": 1617, "y": 1148}, {"x": 1617, "y": 885}], "mask": []}, {"code": 32, "description": "", "states": ["H"], "points": [{"x": 1462, "y": 882}, {"x": 1462, "y": 1135}, {"x": 1531, "y": 1135}, {"x": 1531, "y": 882}], "mask": []}, {"code": 31, "description": "", "states": ["H"], "points": [{"x": 1412, "y": 874}, {"x": 1412, "y": 1151}, {"x": 1472, "y": 1151}, {"x": 1472, "y": 874}], "mask": []}, {"code": 41, "description": "", "states": ["H"], "points": [{"x": 1347, "y": 870}, {"x": 1347, "y": 1134}, {"x": 1416, "y": 1134}, {"x": 1416, "y": 870}], "mask": []}, {"code": 42, "description": "", "states": ["H"], "points": [{"x": 1289, "y": 874}, {"x": 1289, "y": 1126}, {"x": 1356, "y": 1126}, {"x": 1356, "y": 874}], "mask": []}, {"code": 43, "description": "", "states": ["H"], "points": [{"x": 1207, "y": 874}, {"x": 1207, "y": 1137}, {"x": 1293, "y": 1137}, {"x": 1293, "y": 874}], "mask": []}, {"code": 44, "description": "", "states": ["H"], "points": [{"x": 1135, "y": 863}, {"x": 1135, "y": 1155}, {"x": 1224, "y": 1155}, {"x": 1224, "y": 863}], "mask": []}, {"code": 45, "description": "", "states": ["H"], "points": [{"x": 1039, "y": 861}, {"x": 1039, "y": 1141}, {"x": 1134, "y": 1141}, {"x": 1134, "y": 861}], "mask": []}, {"code": 46, "description": "", "states": ["H"], "points": [{"x": 922, "y": 849}, {"x": 868, "y": 1134}, {"x": 1008, "y": 1161}, {"x": 1062, "y": 876}], "mask": []}, {"code": 47, "description": "", "states": ["H"], "points": [{"x": 819, "y": 827}, {"x": 723, "y": 1080}, {"x": 854, "y": 1127}, {"x": 950, "y": 874}], "mask": []}, {"code": 0, "description": "", "states": ["De"], "points": [{"x": 267, "y": 342}, {"x": 267, "y": 1395}, {"x": 2592, "y": 1395}, {"x": 2592, "y": 342}], "mask": []}]}], "representation": [{"BOUNDING_BOX_Maior": "BOUNDING BOX Maior", "children": [{"Ed": "Ed\u00eantulo"}, {"De": "Dentado"}, {"Me": "Maxila ed\u00eantula"}, {"Mne": "Mand\u00edbula ed\u00eantula"}]}, {"BOUNDING_BOX_Menor": "BOUNDING BOX Menor", "children": [{"DA": "DENTES ARTIFICIAIS", "children": [{"Im": "Implante"}, {"Cp": "Coroa prot\u00e9tica unit\u00e1ria"}, {"P": "P\u00f4ntico"}]}, {"DN": "DENTES NATURAIS", "children": [{"H": "H\u00edgido"}, {"Rr": "Raiz Residual"}, {"M3i": "3\u00ba molar Impactado"}, {"M3f": "3\u00ba molar em forma\u00e7\u00e3o"}, {"Te": "Tratamento endod\u00f4ntico"}, {"Ri": "Retentor intrarradicular"}, {"Dc": "Destrui\u00e7\u00e3o coron\u00e1ria"}, {"Di": "Desgaste incisal"}, {"C": "Carie"}, {"R": "Restaurado"}, {"I": "Impactado"}]}, {"DM": "DENTES MISTOS", "children": [{"TeM": "Tratamento endod\u00f4ntico"}, {"RiM": "Retentor intrarradicular"}, {"CpuM": "Coroa prot\u00e9tica unit\u00e1ria"}]}]}], "userId": 5, "studyUID": "2.25.147954431933806485305686905800465263033"}