{"annotations": [{"instanceUID": "2.25.325455169807743917986224719535687290585", "blocks": [{"code": 36, "description": "", "states": ["R"], "points": [{"x": 1636, "y": 866}, {"x": 1813, "y": 1179}, {"x": 2009, "y": 1067}, {"x": 1836, "y": 755}], "mask": []}, {"code": 33, "description": "", "states": ["H"], "points": [{"x": 1493, "y": 832}, {"x": 1493, "y": 1183}, {"x": 1616, "y": 1183}, {"x": 1616, "y": 832}], "mask": []}, {"code": 43, "description": "", "states": ["R", "C"], "points": [{"x": 1240, "y": 807}, {"x": 1172, "y": 1141}, {"x": 1274, "y": 1156}, {"x": 1330, "y": 826}], "mask": []}, {"code": 44, "description": "", "states": ["R"], "points": [{"x": 1188, "y": 781}, {"x": 1081, "y": 1099}, {"x": 1170, "y": 1131}, {"x": 1277, "y": 813}], "mask": []}, {"code": 47, "description": "", "states": ["R"], "points": [{"x": 719, "y": 952}, {"x": 870, "y": 1076}, {"x": 1051, "y": 857}, {"x": 901, "y": 733}], "mask": []}, {"code": 0, "description": "", "states": ["Me"], "points": [{"x": 321, "y": 267}, {"x": 321, "y": 1397}, {"x": 2628, "y": 1397}, {"x": 2628, "y": 267}], "mask": []}]}], "representation": [{"BOUNDING_BOX_Maior": "BOUNDING BOX Maior", "children": [{"Ed": "Ed\u00eantulo"}, {"De": "Dentado"}, {"Me": "Maxila ed\u00eantula"}, {"Mne": "Mand\u00edbula ed\u00eantula"}]}, {"BOUNDING_BOX_Menor": "BOUNDING BOX Menor", "children": [{"DA": "DENTES ARTIFICIAIS", "children": [{"Im": "Implante"}, {"Cp": "Coroa prot\u00e9tica unit\u00e1ria"}, {"P": "P\u00f4ntico"}]}, {"DN": "DENTES NATURAIS", "children": [{"H": "H\u00edgido"}, {"Rr": "Raiz Residual"}, {"M3i": "3\u00ba molar Impactado"}, {"M3f": "3\u00ba molar em forma\u00e7\u00e3o"}, {"Te": "Tratamento endod\u00f4ntico"}, {"Ri": "Retentor intrarradicular"}, {"Dc": "Destrui\u00e7\u00e3o coron\u00e1ria"}, {"Di": "Desgaste incisal"}, {"C": "Carie"}, {"R": "Restaurado"}, {"I": "Impactado"}]}, {"DM": "DENTES MISTOS", "children": [{"TeM": "Tratamento endod\u00f4ntico"}, {"RiM": "Retentor intrarradicular"}, {"CpuM": "Coroa prot\u00e9tica unit\u00e1ria"}]}]}], "userId": 5, "studyUID": "2.25.325455169807743917986224719535687290585"}